{"ID do IMDB":"tt0058593","Orcamento":0,"Popularidade":0.6,"Receita":0,"Paises de Producao":[]}
{"ID do IMDB":"tt0058634","Orcamento":0,"Popularidade":1.896,"Receita":0,"Paises de Producao":["Japan"]}
{"ID do IMDB":"tt0058648","Orcamento":0,"Popularidade":2.851,"Receita":0,"Paises de Producao":["United States of America"]}
{"ID do IMDB":"tt0058661","Orcamento":0,"Popularidade":0.987,"Receita":0,"Paises de Producao":["Denmark"]}
{"ID do IMDB":"tt0058730","Orcamento":0,"Popularidade":1.67,"Receita":0,"Paises de Producao":["Yugoslavia"]}
{"ID do IMDB":"tt0058740","Orcamento":0,"Popularidade":9.407,"Receita":0,"Paises de Producao":["France","Italy"]}
{"ID do IMDB":"tt0058761","Orcamento":0,"Popularidade":1.96,"Receita":0,"Paises de Producao":["United States of America"]}
{"ID do IMDB":"tt0058777","Orcamento":1720000,"Popularidade":13.662,"Receita":8000000,"Paises de Producao":["South Africa","United Kingdom"]}
{"ID do IMDB":"tt0058787","Orcamento":0,"Popularidade":2.528,"Receita":0,"Paises de Producao":["Hungary"]}
{"ID do IMDB":"tt0058863","Orcamento":66000,"Popularidade":6.087,"Receita":306505,"Paises de Producao":["France","Spain"]}
{"ID do IMDB":"tt0058924","Orcamento":0,"Popularidade":1.101,"Receita":0,"Paises de Producao":["Czechoslovakia"]}
{"ID do IMDB":"tt0058945","Orcamento":0,"Popularidade":0.6,"Receita":0,"Paises de Producao":["Poland"]}
{"ID do IMDB":"tt0058946","Orcamento":800000,"Popularidade":14.814,"Receita":964028,"Paises de Producao":["Italy","Algeria"]}
{"ID do IMDB":"tt0058947","Orcamento":6500000,"Popularidade":14.43,"Receita":11118000,"Paises de Producao":["United States of America"]}
{"ID do IMDB":"tt0058948","Orcamento":0,"Popularidade":0.6,"Receita":0,"Paises de Producao":[]}
{"ID do IMDB":"tt0059022","Orcamento":0,"Popularidade":1.24,"Receita":0,"Paises de Producao":["Germany","Italy","United States of America"]}
{"ID do IMDB":"tt0059113","Orcamento":11000000,"Popularidade":26.226,"Receita":111858363,"Paises de Producao":["Italy","United Kingdom","United States of America"]}
{"ID do IMDB":"tt0059195","Orcamento":0,"Popularidade":0.6,"Receita":0,"Paises de Producao":[]}
{"ID do IMDB":"tt0059208","Orcamento":0,"Popularidade":1.289,"Receita":0,"Paises de Producao":["Romania","France"]}
{"ID do IMDB":"tt0059268","Orcamento":0,"Popularidade":1.757,"Receita":0,"Paises de Producao":["United Kingdom"]}
{"ID do IMDB":"tt0059274","Orcamento":0,"Popularidade":9.788,"Receita":0,"Paises de Producao":["United Kingdom"]}
{"ID do IMDB":"tt0059309","Orcamento":4200000,"Popularidade":13.825,"Receita":0,"Paises de Producao":["United States of America"]}
{"ID do IMDB":"tt0059323","Orcamento":0,"Popularidade":4.364,"Receita":0,"Paises de Producao":["Italy","Soviet Union"]}
{"ID do IMDB":"tt0059334","Orcamento":0,"Popularidade":0.994,"Receita":0,"Paises de Producao":["United Kingdom"]}
{"ID do IMDB":"tt0059358","Orcamento":0,"Popularidade":8.504,"Receita":0,"Paises de Producao":["United States of America"]}
{"ID do IMDB":"tt0059418","Orcamento":3800000,"Popularidade":14.69,"Receita":14873,"Paises de Producao":["United States of America"]}
{"ID do IMDB":"tt0059437","Orcamento":0,"Popularidade":2.204,"Receita":0,"Paises de Producao":["United States of America"]}
{"ID do IMDB":"tt0059458","Orcamento":0,"Popularidade":0.6,"Receita":0,"Paises de Producao":["Poland","France","Germany"]}
{"ID do IMDB":"tt0059494","Orcamento":0,"Popularidade":0.6,"Receita":0,"Paises de Producao":["Greece","United States of America"]}
{"ID do IMDB":"tt0059518","Orcamento":0,"Popularidade":6.203,"Receita":0,"Paises de Producao":["Japan","United States of America"]}
{"ID do IMDB":"tt0059527","Orcamento":0,"Popularidade":6.558,"Receita":1450000,"Paises de Producao":["Czechoslovakia"]}
{"ID do IMDB":"tt0059529","Orcamento":0,"Popularidade":3.479,"Receita":0,"Paises de Producao":["Soviet Union"]}
{"ID do IMDB":"tt0059539","Orcamento":0,"Popularidade":1.491,"Receita":0,"Paises de Producao":["United States of America","Philippines"]}
{"ID do IMDB":"tt0059549","Orcamento":115000,"Popularidade":11.758,"Receita":3700000,"Paises de Producao":["United Kingdom"]}
{"ID do IMDB":"tt0059593","Orcamento":0,"Popularidade":1.121,"Receita":0,"Paises de Producao":["Poland"]}
{"ID do IMDB":"tt0059611","Orcamento":0,"Popularidade":1.021,"Receita":0,"Paises de Producao":["Spain"]}
{"ID do IMDB":"tt0059638","Orcamento":0,"Popularidade":0.964,"Receita":0,"Paises de Producao":["United States of America","Philippines"]}
{"ID do IMDB":"tt0059693","Orcamento":0,"Popularidade":1.702,"Receita":0,"Paises de Producao":["United Kingdom","United States of America"]}
{"ID do IMDB":"tt0059711","Orcamento":0,"Popularidade":8.705,"Receita":0,"Paises de Producao":["United States of America"]}
{"ID do IMDB":"tt0059712","Orcamento":0,"Popularidade":11.347,"Receita":0,"Paises de Producao":["United States of America"]}
{"ID do IMDB":"tt0059715","Orcamento":0,"Popularidade":6.48,"Receita":0,"Paises de Producao":["Japan"]}
{"ID do IMDB":"tt0059724","Orcamento":0,"Popularidade":3.73,"Receita":0,"Paises de Producao":["Germany","United States of America"]}
{"ID do IMDB":"tt0059732","Orcamento":0,"Popularidade":4.597,"Receita":0,"Paises de Producao":["France","Germany","Italy","Yugoslavia"]}
{"ID do IMDB":"tt0059776","Orcamento":0,"Popularidade":4.111,"Receita":0,"Paises de Producao":["Hungary"]}
{"ID do IMDB":"tt0059812","Orcamento":0,"Popularidade":1.154,"Receita":0,"Paises de Producao":["Hungary"]}
{"ID do IMDB":"tt0059825","Orcamento":5800000,"Popularidade":11.231,"Receita":6800000,"Paises de Producao":["France","Italy","United States of America"]}
{"ID do IMDB":"tt0059828","Orcamento":0,"Popularidade":1.318,"Receita":0,"Paises de Producao":["Spain","Italy"]}
{"ID do IMDB":"tt0059829","Orcamento":0,"Popularidade":1.388,"Receita":0,"Paises de Producao":["Yugoslavia"]}
{"ID do IMDB":"tt0059853","Orcamento":0,"Popularidade":1.121,"Receita":0,"Paises de Producao":["France","United Kingdom","United States of America"]}
{"ID do IMDB":"tt0059856","Orcamento":0,"Popularidade":7.638,"Receita":0,"Paises de Producao":["Italy"]}
{"ID do IMDB":"tt0059884","Orcamento":0,"Popularidade":7.807,"Receita":0,"Paises de Producao":["Soviet Union"]}
{"ID do IMDB":"tt0059885","Orcamento":5760000,"Popularidade":12.902,"Receita":0,"Paises de Producao":["United States of America"]}
{"ID do IMDB":"tt0060098","Orcamento":0,"Popularidade":3.446,"Receita":0,"Paises de Producao":["United States of America"]}
{"ID do IMDB":"tt0060299","Orcamento":0,"Popularidade":1.963,"Receita":0,"Paises de Producao":["Denmark"]}
{"ID do IMDB":"tt0060309","Orcamento":0,"Popularidade":1.96,"Receita":0,"Paises de Producao":["Soviet Union"]}
{"ID do IMDB":"tt0060318","Orcamento":0,"Popularidade":1.3,"Receita":0,"Paises de Producao":["Soviet Union"]}
{"ID do IMDB":"tt0060327","Orcamento":0,"Popularidade":0.628,"Receita":0,"Paises de Producao":["Poland"]}
{"ID do IMDB":"tt0060334","Orcamento":0,"Popularidade":0.722,"Receita":0,"Paises de Producao":[]}
{"ID do IMDB":"tt0060352","Orcamento":0,"Popularidade":2.048,"Receita":0,"Paises de Producao":["Italy","Spain"]}
{"ID do IMDB":"tt0060474","Orcamento":0,"Popularidade":22.743,"Receita":0,"Paises de Producao":["France","United Kingdom"]}
{"ID do IMDB":"tt0060481","Orcamento":0,"Popularidade":3.328,"Receita":0,"Paises de Producao":["Sweden","France"]}
{"ID do IMDB":"tt0060531","Orcamento":0,"Popularidade":2.364,"Receita":0,"Paises de Producao":["United States of America"]}
{"ID do IMDB":"tt0060568","Orcamento":0,"Popularidade":2.6,"Receita":0,"Paises de Producao":["Israel","United Kingdom","United States of America"]}
{"ID do IMDB":"tt0060570","Orcamento":0,"Popularidade":1.581,"Receita":0,"Paises de Producao":["Spain","Italy"]}
{"ID do IMDB":"tt0060583","Orcamento":0,"Popularidade":1.051,"Receita":0,"Paises de Producao":["Poland","Germany"]}
{"ID do IMDB":"tt0060597","Orcamento":0,"Popularidade":2.569,"Receita":0,"Paises de Producao":["Czechoslovakia"]}
{"ID do IMDB":"tt0060630","Orcamento":0,"Popularidade":4.207,"Receita":0,"Paises de Producao":["France"]}
{"ID do IMDB":"tt0060637","Orcamento":0,"Popularidade":10.024,"Receita":0,"Paises de Producao":["United States of America"]}
{"ID do IMDB":"tt0060673","Orcamento":0,"Popularidade":1.258,"Receita":0,"Paises de Producao":["France"]}
{"ID do IMDB":"tt0060780","Orcamento":0,"Popularidade":0.6,"Receita":0,"Paises de Producao":["Spain"]}
{"ID do IMDB":"tt0060814","Orcamento":0,"Popularidade":10.911,"Receita":0,"Paises de Producao":["France","United States of America"]}
{"ID do IMDB":"tt0060846","Orcamento":0,"Popularidade":0.719,"Receita":0,"Paises de Producao":["Yugoslavia"]}
{"ID do IMDB":"tt0060847","Orcamento":0,"Popularidade":2.024,"Receita":0,"Paises de Producao":["Poland"]}
{"ID do IMDB":"tt0060850","Orcamento":0,"Popularidade":0.699,"Receita":0,"Paises de Producao":["Poland"]}
{"ID do IMDB":"tt0060908","Orcamento":0,"Popularidade":5.401,"Receita":0,"Paises de Producao":["France","Italy"]}
{"ID do IMDB":"tt0060921","Orcamento":0,"Popularidade":9.47,"Receita":0,"Paises de Producao":["United States of America"]}
{"ID do IMDB":"tt0060932","Orcamento":0,"Popularidade":1.831,"Receita":0,"Paises de Producao":["Yugoslavia"]}
{"ID do IMDB":"tt0060999","Orcamento":0,"Popularidade":1.384,"Receita":0,"Paises de Producao":["Mexico"]}
{"ID do IMDB":"tt0061099","Orcamento":0,"Popularidade":1.4,"Receita":0,"Paises de Producao":["United States of America"]}
{"ID do IMDB":"tt0061176","Orcamento":0,"Popularidade":7.644,"Receita":0,"Paises de Producao":["United States of America"]}
{"ID do IMDB":"tt0061389","Orcamento":0,"Popularidade":3.228,"Receita":0,"Paises de Producao":["United States of America"]}
{"ID do IMDB":"tt0061530","Orcamento":0,"Popularidade":0.6,"Receita":0,"Paises de Producao":["Yugoslavia"]}
{"ID do IMDB":"tt0061537","Orcamento":0,"Popularidade":4.454,"Receita":0,"Paises de Producao":["Hungary","Soviet Union"]}
{"ID do IMDB":"tt0061578","Orcamento":5400000,"Popularidade":43.595,"Receita":45300000,"Paises de Producao":["United Kingdom","United States of America"]}
{"ID do IMDB":"tt0061616","Orcamento":0,"Popularidade":1.317,"Receita":0,"Paises de Producao":["Hungary"]}
{"ID do IMDB":"tt0061667","Orcamento":0,"Popularidade":1.613,"Receita":0,"Paises de Producao":["United States of America"]}
{"ID do IMDB":"tt0061693","Orcamento":0,"Popularidade":3.21,"Receita":0,"Paises de Producao":["France","Germany","Italy"]}
{"ID do IMDB":"tt0061746","Orcamento":0,"Popularidade":0.968,"Receita":0,"Paises de Producao":["Germany","Italy"]}
{"ID do IMDB":"tt0061773","Orcamento":0,"Popularidade":5.339,"Receita":0,"Paises de Producao":["Italy"]}
{"ID do IMDB":"tt0061789","Orcamento":0,"Popularidade":3.226,"Receita":0,"Paises de Producao":["United Kingdom"]}
{"ID do IMDB":"tt0061802","Orcamento":0,"Popularidade":2.03,"Receita":0,"Paises de Producao":["East Germany"]}
{"ID do IMDB":"tt0061854","Orcamento":0,"Popularidade":1.012,"Receita":0,"Paises de Producao":["Yugoslavia"]}
{"ID do IMDB":"tt0061876","Orcamento":0,"Popularidade":4.084,"Receita":0,"Paises de Producao":["Soviet Union"]}
{"ID do IMDB":"tt0061880","Orcamento":0,"Popularidade":0.6,"Receita":0,"Paises de Producao":["Poland"]}
{"ID do IMDB":"tt0061913","Orcamento":0,"Popularidade":1.491,"Receita":0,"Paises de Producao":["France"]}
{"ID do IMDB":"tt0062041","Orcamento":0,"Popularidade":4.738,"Receita":0,"Paises de Producao":["Japan"]}
{"ID do IMDB":"tt0062245","Orcamento":0,"Popularidade":1.72,"Receita":0,"Paises de Producao":["Soviet Union"]}
{"ID do IMDB":"tt0062270","Orcamento":0,"Popularidade":0.6,"Receita":0,"Paises de Producao":["Spain","Italy"]}
{"ID do IMDB":"tt0062272","Orcamento":0,"Popularidade":1.199,"Receita":0,"Paises de Producao":["Soviet Union"]}
{"ID do IMDB":"tt0062282","Orcamento":0,"Popularidade":0.6,"Receita":0,"Paises de Producao":["United States of America"]}
